continualUtils/__init__.py
continualUtils/_version.py
continualUtils/benchmarks/__init__.py
continualUtils/benchmarks/clickme.py
continualUtils/benchmarks/datasets/__init__.py
continualUtils/benchmarks/datasets/clickme.py
continualUtils/benchmarks/datasets/ffcv_transforms.py
continualUtils/benchmarks/datasets/normalizations.py
continualUtils/evaluation/__init__.py
continualUtils/evaluation/harmonizer_metrics.py
continualUtils/evaluation/learning_rate_metrics.py
continualUtils/evaluation/saliency_map_metrics.py
continualUtils/evaluation/step_epoch_metrics.py
continualUtils/explain/__init__.py
continualUtils/explain/harmonizer_plugin.py
continualUtils/explain/losses/__init__.py
continualUtils/explain/losses/harmonizer_loss.py
continualUtils/explain/losses/lwm_loss.py
continualUtils/explain/losses/sgt_loss.py
continualUtils/explain/losses/total_variation_loss.py
continualUtils/explain/lwm_plugin.py
continualUtils/explain/sgt_plugin.py
continualUtils/explain/tools/__init__.py
continualUtils/explain/tools/saliency_map.py
continualUtils/explain/tools/standardize_cut.py
continualUtils/general/rescale_batch.py
continualUtils/models/__init__.py
continualUtils/models/_base.py
continualUtils/models/_patched_bn.py
continualUtils/models/alexnet.py
continualUtils/models/cifarnet.py
continualUtils/models/clip.py
continualUtils/models/cvt.py
continualUtils/models/deit.py
continualUtils/models/resnet.py
continualUtils/models/simple.py
continualUtils/models/utils.py
continualUtils/models/wide_resnet.py
continualUtils/schedulers/__init__.py
continualUtils/schedulers/cosine_lr.py
continualUtils/schedulers/lr_finder.py
continualUtils/security/__init__.py
continualUtils/security/adversarial_medical_plugin.py
continualUtils/security/adversarial_replay.py
continualUtils/security/adversarial_saliency_plugin.py
continualUtils/security/losses/__init__.py
continualUtils/security/losses/adversarial_attack_loss.py
continualUtils/security/tools/universal_adversarial_perturbation.py
continualtrain-0.0.0.dist-info/METADATA
continualtrain-0.0.0.dist-info/WHEEL
continualtrain-0.0.0.dist-info/entry_points.txt
continualtrain-0.0.0.dist-info/RECORD
