Metadata-Version: 2.1
Name: continualtrain
Version: 0.0.0
Summary: Train CL models in a Docker container
License: MIT
Author: Nishant S. Aswani
Author-email: nishantaswani@nyu.edu
Requires-Python: >=3.8.1,<3.11
Classifier: License :: OSI Approved :: MIT License
Classifier: Programming Language :: Python :: 3
Classifier: Programming Language :: Python :: 3.9
Classifier: Programming Language :: Python :: 3.10
Requires-Dist: requests
Requires-Dist: spython
Requires-Dist: tomlkit
Requires-Dist: typer[all]
